[
  {
    "id": "1",
    "name": "Hakuho",
    "division": "Makuuchi",
    "rank": "yokozuna",
    "rankNumber": null,
    "rankDirection": "east",
    "placeOfBirth": "Mongolia",
    "age": 34,
    "injured": true,
    "status": "active"
  },
  {
    "id": "2",
    "name": "Enho",
    "division": "Makuuchi",
    "rank": "maegashira",
    "rankNumber": 5,
    "rankDirection": "west",
    "placeOfBirth": "Japan",
    "age": 25,
    "injured": false,
    "status": "active"
  },
  {
    "id": "3",
    "name": "Abi",
    "division": "Makuuchi",
    "rank": "komusubi",
    "rankNumber": null,
    "rankDirection": "east",
    "placeOfBirth": "Japan",
    "age": 25,
    "injured": false,
    "status": "active"
  },
  {
    "id": "4",
    "name": "Ishiura",
    "division": "Makuuchi",
    "rank": "maegashira",
    "rankNumber": 10,
    "rankDirection": "west",
    "placeOfBirth": "Japan",
    "age": 30,
    "injured": false,
    "status": "active"
  },
  {
    "id": "5",
    "name": "Asanoyama",
    "division": "Makuuchi",
    "rank": "sekiwake",
    "rankNumber": null,
    "rankDirection": "east",
    "placeOfBirth": "Japan",
    "age": 30,
    "injured": false,
    "status": "active"
  },
  {
    "id": "6",
    "name": "Tochinoshin",
    "division": "Makuuchi",
    "rank": "maegashira",
    "rankNumber": 6,
    "rankDirection": "west",
    "placeOfBirth": "Georgian",
    "age": 32,
    "injured": false,
    "status": "active"
  },
  {
    "id": "7",
    "name": "Goeido",
    "division": "Makuuchi",
    "rank": "ozeki",
    "rankNumber": null,
    "rankDirection": "west",
    "placeOfBirth": "Japan",
    "age": 33,
    "injured": false,
    "status": "retired"
  },
  {
    "id": "8",
    "name": "Kakuryu",
    "division": "Makuuchi",
    "rank": "yokozuna",
    "rankNumber": null,
    "rankDirection": "west",
    "placeOfBirth": "Mongolia",
    "age": 34,
    "injured": false,
    "status": "active"
  },
  {
    "id": "9",
    "name": "Takakeisho",
    "division": "Makuuchi",
    "rank": "ozeki",
    "rankNumber": null,
    "rankDirection": "east",
    "placeOfBirth": "Japan",
    "age": 34,
    "injured": false,
    "status": "active"
  },
  {
    "id": "10",
    "name": "Takayasu",
    "division": "Makuuchi",
    "rank": "sekiwake",
    "rankNumber": null,
    "rankDirection": "west",
    "placeOfBirth": "Japan",
    "age": 34,
    "injured": false,
    "status": "active"
  },
  {
    "id": "11",
    "name": "Daieisho",
    "division": "Makuuchi",
    "rank": "komusubi",
    "rankNumber": null,
    "rankDirection": "west",
    "placeOfBirth": "Japan",
    "age": 34,
    "injured": false,
    "status": "active"
  },
  {
    "id": "12",
    "name": "Endo",
    "division": "Makuuchi",
    "rank": "maegashira",
    "rankNumber": 1,
    "rankDirection": "east",
    "placeOfBirth": "Japan",
    "age": 34,
    "injured": false,
    "status": "active"
  },
  {
    "id": "13",
    "name": "Myogiryu",
    "division": "Makuuchi",
    "rank": "maegashira",
    "rankNumber": 1,
    "rankDirection": "west",
    "placeOfBirth": "Japan",
    "age": 34,
    "injured": false,
    "status": "active"
  },
  {
    "id": "14",
    "name": "Hokutofuji",
    "division": "Makuuchi",
    "rank": "maegashira",
    "rankNumber": 2,
    "rankDirection": "east",
    "placeOfBirth": "Japan",
    "age": 34,
    "injured": false,
    "status": "active"
  },
  {
    "id": "15",
    "name": "Mitakeumi",
    "division": "Makuuchi",
    "rank": "maegashira",
    "rankNumber": 2,
    "rankDirection": "west",
    "placeOfBirth": "Japan",
    "age": 34,
    "injured": false,
    "status": "active"
  },
  {
    "id": "16",
    "name": "Tamawashi",
    "division": "Makuuchi",
    "rank": "maegashira",
    "rankNumber": 3,
    "rankDirection": "east",
    "placeOfBirth": "Mongolia",
    "age": 34,
    "injured": false,
    "status": "active"
  },
  {
    "id": "17",
    "name": "Kotoyuki",
    "division": "Makuuchi",
    "rank": "maegashira",
    "rankNumber": 3,
    "rankDirection": "west",
    "placeOfBirth": "Japan",
    "age": 34,
    "injured": false,
    "status": "active"
  },
  {
    "id": "18",
    "name": "Okinoumi",
    "division": "Makuuchi",
    "rank": "maegashira",
    "rankNumber": 4,
    "rankDirection": "east",
    "placeOfBirth": "Japan",
    "age": 34,
    "injured": false,
    "status": "active"
  },
  {
    "id": "19",
    "name": "Shodai",
    "division": "Makuuchi",
    "rank": "maegashira",
    "rankNumber": 4,
    "rankDirection": "west",
    "placeOfBirth": "Japan",
    "age": 34,
    "injured": false,
    "status": "active"
  },
  {
    "id": "20",
    "name": "Meisei",
    "division": "Makuuchi",
    "rank": "maegashira",
    "rankNumber": 5,
    "rankDirection": "east",
    "placeOfBirth": "Japan",
    "age": 34,
    "injured": false,
    "status": "active"
  },
  {
    "id": "21",
    "name": "Takarafuji",
    "division": "Makuuchi",
    "rank": "maegashira",
    "rankNumber": 6,
    "rankDirection": "east",
    "placeOfBirth": "Japan",
    "age": 34,
    "injured": false,
    "status": "active"
  },
  {
    "id": "22",
    "name": "Shohozan",
    "division": "Makuuchi",
    "rank": "maegashira",
    "rankNumber": 7,
    "rankDirection": "east",
    "placeOfBirth": "Japan",
    "age": 34,
    "injured": false,
    "status": "active"
  },
  {
    "id": "23",
    "name": "Onosho",
    "division": "Makuuchi",
    "rank": "maegashira",
    "rankNumber": 7,
    "rankDirection": "west",
    "placeOfBirth": "Japan",
    "age": 34,
    "injured": false,
    "status": "active"
  },
  {
    "id": "24",
    "name": "Aoiyama",
    "division": "Makuuchi",
    "rank": "maegashira",
    "rankNumber": 8,
    "rankDirection": "east",
    "placeOfBirth": "Bulgarian",
    "age": 34,
    "injured": false,
    "status": "active"
  },
  {
    "id": "25",
    "name": "Ryuden",
    "division": "Makuuchi",
    "rank": "maegashira",
    "rankNumber": 8,
    "rankDirection": "west",
    "placeOfBirth": "Japan",
    "age": 34,
    "injured": false,
    "status": "active"
  },
  {
    "id": "26",
    "name": "Takanosho",
    "division": "Makuuchi",
    "rank": "maegashira",
    "rankNumber": 9,
    "rankDirection": "east",
    "placeOfBirth": "Japan",
    "age": 34,
    "injured": false,
    "status": "active"
  },
  {
    "id": "27",
    "name": "Yutakayama",
    "division": "Makuuchi",
    "rank": "maegashira",
    "rankNumber": 9,
    "rankDirection": "west",
    "placeOfBirth": "Japan",
    "age": 34,
    "injured": false,
    "status": "active"
  },
  {
    "id": "28",
    "name": "Sadanoumi",
    "division": "Makuuchi",
    "rank": "maegashira",
    "rankNumber": 10,
    "rankDirection": "east",
    "placeOfBirth": "Japan",
    "age": 34,
    "injured": false,
    "status": "active"
  },
  {
    "id": "29",
    "name": "Chiyotairyu",
    "division": "Makuuchi",
    "rank": "maegashira",
    "rankNumber": 11,
    "rankDirection": "east",
    "placeOfBirth": "Japan",
    "age": 34,
    "injured": false,
    "status": "active"
  },
  {
    "id": "30",
    "name": "Kagayaki",
    "division": "Makuuchi",
    "rank": "maegashira",
    "rankNumber": 11,
    "rankDirection": "west",
    "placeOfBirth": "Japan",
    "age": 34,
    "injured": false,
    "status": "active"
  },
  {
    "id": "31",
    "name": "Tsurugisho",
    "division": "Makuuchi",
    "rank": "maegashira",
    "rankNumber": 12,
    "rankDirection": "east",
    "placeOfBirth": "Japan",
    "age": 34,
    "injured": false,
    "status": "active"
  },
  {
    "id": "32",
    "name": "Chiyomaru",
    "division": "Makuuchi",
    "rank": "maegashira",
    "rankNumber": 12,
    "rankDirection": "west",
    "placeOfBirth": "Japan",
    "age": 34,
    "injured": false,
    "status": "active"
  },
  {
    "id": "33",
    "name": "Kotoshogiku",
    "division": "Makuuchi",
    "rank": "maegashira",
    "rankNumber": 13,
    "rankDirection": "east",
    "placeOfBirth": "Japan",
    "age": 34,
    "injured": false,
    "status": "active"
  },
  {
    "id": "34",
    "name": "Kotoeko",
    "division": "Makuuchi",
    "rank": "maegashira",
    "rankNumber": 13,
    "rankDirection": "west",
    "placeOfBirth": "Japan",
    "age": 34,
    "injured": false,
    "status": "active"
  },
  {
    "id": "35",
    "name": "Terutsuyoshi",
    "division": "Makuuchi",
    "rank": "maegashira",
    "rankNumber": 14,
    "rankDirection": "east",
    "placeOfBirth": "Japan",
    "age": 34,
    "injured": false,
    "status": "active"
  },
  {
    "id": "36",
    "name": "Shimanoumi",
    "division": "Makuuchi",
    "rank": "maegashira",
    "rankNumber": 14,
    "rankDirection": "west",
    "placeOfBirth": "Japan",
    "age": 34,
    "injured": false,
    "status": "active"
  },
  {
    "id": "37",
    "name": "Azumaryu",
    "division": "Makuuchi",
    "rank": "maegashira",
    "rankNumber": 15,
    "rankDirection": "east",
    "placeOfBirth": "Mongolia",
    "age": 34,
    "injured": false,
    "status": "active"
  },
  {
    "id": "38",
    "name": "Ikioi",
    "division": "Makuuchi",
    "rank": "maegashira",
    "rankNumber": 15,
    "rankDirection": "west",
    "placeOfBirth": "Japan",
    "age": 34,
    "injured": false,
    "status": "active"
  },
  {
    "id": "39",
    "name": "Tochiozan",
    "division": "Makuuchi",
    "rank": "maegashira",
    "rankNumber": 16,
    "rankDirection": "east",
    "placeOfBirth": "Japan",
    "age": 34,
    "injured": false,
    "status": "active"
  },
  {
    "id": "40",
    "name": "Kaisei",
    "division": "Makuuchi",
    "rank": "maegashira",
    "rankNumber": 16,
    "rankDirection": "west",
    "placeOfBirth": "Brazilian",
    "age": 34,
    "injured": false,
    "status": "active"
  },
  {
    "id": "41",
    "name": "Kiribayama",
    "division": "Makuuchi",
    "rank": "maegashira",
    "rankNumber": 17,
    "rankDirection": "east",
    "placeOfBirth": "Mongolia",
    "age": 34,
    "injured": false,
    "status": "active"
  },
  {
    "id": "42",
    "name": "Tokushoryu",
    "division": "Makuuchi",
    "rank": "maegashira",
    "rankNumber": 17,
    "rankDirection": "west",
    "placeOfBirth": "Japan",
    "age": 34,
    "injured": false,
    "status": "active"
  },
  {
    "id": "43",
    "name": "Tomokaze",
    "division": "Makuuchi",
    "rank": "juryo",
    "rankNumber": 1,
    "rankDirection": "east",
    "placeOfBirth": "Japan",
    "age": 34,
    "injured": false,
    "status": "active"
  },
  {
    "id": "44",
    "name": "Chiyoshoma",
    "division": "Makuuchi",
    "rank": "juryo",
    "rankNumber": 1,
    "rankDirection": "west",
    "placeOfBirth": "Mongolia",
    "age": 34,
    "injured": false,
    "status": "active"
  },
  {
    "id": "45",
    "name": "Kotonowaka",
    "division": "Makuuchi",
    "rank": "juryo",
    "rankNumber": 2,
    "rankDirection": "east",
    "placeOfBirth": "Japan",
    "age": 34,
    "injured": false,
    "status": "active"
  },
  {
    "id": "46",
    "name": "Hidenoumi",
    "division": "Makuuchi",
    "rank": "juryo",
    "rankNumber": 2,
    "rankDirection": "west",
    "placeOfBirth": "Japan",
    "age": 34,
    "injured": false,
    "status": "active"
  },
  {
    "id": "47",
    "name": "Daishomaru",
    "division": "Makuuchi",
    "rank": "juryo",
    "rankNumber": 3,
    "rankDirection": "east",
    "placeOfBirth": "Japan",
    "age": 34,
    "injured": false,
    "status": "active"
  },
  {
    "id": "48",
    "name": "Kizakiumi",
    "division": "Makuuchi",
    "rank": "juryo",
    "rankNumber": 3,
    "rankDirection": "west",
    "placeOfBirth": "Japan",
    "age": 34,
    "injured": false,
    "status": "active"
  }
]
